dotenv/__init__.py
dotenv/cli.py
dotenv/compat.py
dotenv/ipython.py
dotenv/main.py
dotenv/parser.py
dotenv/py.typed
dotenv/variables.py
dotenv/version.py
python_dotenv_yaml-0.17.1.dist-info/LICENSE
python_dotenv_yaml-0.17.1.dist-info/METADATA
python_dotenv_yaml-0.17.1.dist-info/WHEEL
python_dotenv_yaml-0.17.1.dist-info/entry_points.txt
python_dotenv_yaml-0.17.1.dist-info/top_level.txt
python_dotenv_yaml-0.17.1.dist-info/RECORD
