Metadata-Version: 2.1
Name: python-dotenv-yaml
Version: 0.17.1
Summary: Read key-value pairs from a .env file and set them as environment variables -> with support for yaml syntax
Home-page: https://github.com/theskumar/python-dotenv
Author: Saurabh Kumar
Author-email: me+github@saurabh-kumar.com
License: UNKNOWN
Keywords: environment variables,deployments,settings,env,dotenv,configurations,python
Platform: UNKNOWN
Classifier: Development Status :: 5 - Production/Stable
Classifier: Programming Language :: Python
Classifier: Programming Language :: Python :: 2
Classifier: Programming Language :: Python :: 2.7
Classifier: Programming Language :: Python :: 3
Classifier: Programming Language :: Python :: 3.5
Classifier: Programming Language :: Python :: 3.6
Classifier: Programming Language :: Python :: 3.7
Classifier: Programming Language :: Python :: 3.8
Classifier: Programming Language :: Python :: 3.9
Classifier: Programming Language :: Python :: Implementation :: PyPy
Classifier: Intended Audience :: Developers
Classifier: Intended Audience :: System Administrators
Classifier: License :: OSI Approved :: BSD License
Classifier: Operating System :: OS Independent
Classifier: Topic :: System :: Systems Administration
Classifier: Topic :: Utilities
Classifier: Environment :: Web Environment
Requires-Dist: typing ; python_version < "3.5"
Provides-Extra: cli
Requires-Dist: click (>=5.0) ; extra == 'cli'
